piland_http_health_checker/__init__.py
piland_http_health_checker/main.py
piland_http_health_checker-0.3.0.dist-info/entry_points.txt
piland_http_health_checker-0.3.0.dist-info/METADATA
piland_http_health_checker-0.3.0.dist-info/WHEEL
piland_http_health_checker-0.3.0.dist-info/RECORD
